pytest_patterns/__about__.py
pytest_patterns/__init__.py
pytest_patterns/plugin.py
pytest_patterns-0.3.0.dist-info/METADATA
pytest_patterns-0.3.0.dist-info/WHEEL
pytest_patterns-0.3.0.dist-info/entry_points.txt
pytest_patterns-0.3.0.dist-info/RECORD
