Metadata-Version: 2.1
Name: pytest-patterns
Version: 0.3.0
Summary: pytest plugin to make testing complicated long string output easy to write and easy to debug
Project-URL: Documentation, https://github.com/unknown/pytest-patterns#readme
Project-URL: Issues, https://github.com/unknown/pytest-patterns/issues
Project-URL: Source, https://github.com/unknown/pytest-patterns
Author-email: Christian Theune <ct@flyingcircus.io>
License-Expression: MIT
Classifier: Development Status :: 4 - Beta
Classifier: Framework :: Pytest
Classifier: Programming Language :: Python
Classifier: Programming Language :: Python :: 3 :: Only
Classifier: Programming Language :: Python :: 3.7
Classifier: Programming Language :: Python :: 3.8
Classifier: Programming Language :: Python :: 3.9
Classifier: Programming Language :: Python :: 3.10
Classifier: Programming Language :: Python :: 3.11
Classifier: Programming Language :: Python :: 3.12
Classifier: Programming Language :: Python :: Implementation :: CPython
Classifier: Programming Language :: Python :: Implementation :: PyPy
Requires-Python: >=3.7
Requires-Dist: pytest>=6
